dishpill/__init__.py
dishpill/core.py
dishpill/error.py
dishpill/logger.py
dishpill/py.typed
dishpill/version.py
dishpill/envs/__init__.py
dishpill/envs/registration.py
dishpill/envs/dishgames/__init__.py
dishpill/envs/dishgames/pong.py
dishpill/spaces/__init__.py
dishpill/spaces/discrete.py
dishpill/spaces/space.py
dishpill/utils/__init__.py
dishpill/utils/colorize.py
dishpill/utils/seeding.py
dishpill/wrappers/__init__.py
dishpill/wrappers/order_enforcing.py
dishpill-0.0.6.dist-info/LICENSE.md
dishpill-0.0.6.dist-info/METADATA
dishpill-0.0.6.dist-info/WHEEL
dishpill-0.0.6.dist-info/top_level.txt
dishpill-0.0.6.dist-info/RECORD
